fennel/__init__.py
fennel/__main__.py
fennel/app.py
fennel/cli.py
fennel/client/__init__.py
fennel/client/actions.py
fennel/client/aio/__init__.py
fennel/client/aio/actions.py
fennel/client/aio/results.py
fennel/client/aio/state.py
fennel/client/aio/task.py
fennel/client/aio/waiting.py
fennel/client/results.py
fennel/client/state.py
fennel/client/task.py
fennel/client/waiting.py
fennel/exceptions.py
fennel/job.py
fennel/keys.py
fennel/logging.py
fennel/models.py
fennel/settings.py
fennel/status.py
fennel/utils.py
fennel/worker/__init__.py
fennel/worker/broker.py
fennel/worker/discovery.py
fennel/worker/executor.py
fennel/worker/lua/maintenance.lua
fennel/worker/lua/schedule.lua
fennel/worker/worker.py
fennel-0.3.0.dist-info/entry_points.txt
fennel-0.3.0.dist-info/LICENSE
fennel-0.3.0.dist-info/WHEEL
fennel-0.3.0.dist-info/METADATA
fennel-0.3.0.dist-info/RECORD
