Metadata-Version: 2.1
Name: fennel
Version: 0.3.0
Summary: A task queue for Python based on Redis Streams.
Home-page: https://fennel.dev
License: MIT
Keywords: task,queue,background,redis,async
Author: Matt Westcott
Author-email: m.westcott@gmail.com
Requires-Python: >=3.7,<4.0
Classifier: License :: OSI Approved :: MIT License
Classifier: Programming Language :: Python :: 3
Classifier: Programming Language :: Python :: 3.7
Classifier: Programming Language :: Python :: 3.8
Requires-Dist: anyio (>=2.0.0-beta.2,<3.0.0)
Requires-Dist: aredis (>=1.1.8,<2.0.0)
Requires-Dist: click (>=7.0,<8.0)
Requires-Dist: colorama (>=0.4.1,<0.5.0)
Requires-Dist: hiredis (>=1.1.0,<2.0.0)
Requires-Dist: pydantic (>=1.5,<2.0)
Requires-Dist: redis (>=3.3,<4.0)
Requires-Dist: structlog (>=20.0,<21.0)
Requires-Dist: uvloop (>=0.14.0,<0.15.0)
Project-URL: Repository, https://github.com/mjwestcott/fennel
